frontoffice/__init__.py
frontoffice/api_client.py
frontoffice/configuration.py
frontoffice/exceptions.py
frontoffice/rest.py
frontoffice/api/__init__.py
frontoffice/api/contactgegevens_api.py
frontoffice/api/developer_tools_api.py
frontoffice/api/persoonsgegevens_api.py
frontoffice/api/search_api.py
frontoffice/models/__init__.py
frontoffice/models/adres_mutatie.py
frontoffice/models/contact.py
frontoffice/models/contactgegevens_event.py
frontoffice/models/contactgegevens_event_input.py
frontoffice/models/contactpersoon_gegevens.py
frontoffice/models/datum_delen.py
frontoffice/models/http_validation_error.py
frontoffice/models/partnerschap.py
frontoffice/models/persoon_contact_gegevens.py
frontoffice/models/persoons_gegevens.py
frontoffice/models/persoons_gegevens_basic.py
frontoffice/models/settings.py
frontoffice/models/validation_error.py
frontoffice/models/werkgegever_contact_gegevens.py
pi_team_frontoffice_client-1.2.0.dist-info/METADATA
pi_team_frontoffice_client-1.2.0.dist-info/WHEEL
pi_team_frontoffice_client-1.2.0.dist-info/top_level.txt
pi_team_frontoffice_client-1.2.0.dist-info/RECORD
